Metadata-Version: 2.1
Name: math3d
Version: 4.0.0
Summary: 3D Special Euclidean mathematics package for Python.
Home-page: https://codeberg.org/moli/pymath3d
Author: Morten Lind
Author-email: morten@lind.fairuse.org
License: GNU Lesser General Public License v3 (LGPLv3)
Classifier: Development Status :: 5 - Production/Stable
Classifier: License :: OSI Approved :: GNU Lesser General Public License v3 (LGPLv3)
Classifier: Natural Language :: English
Classifier: Programming Language :: Python
Classifier: Topic :: Scientific/Engineering
Provides: math3d
License-File: COPYING.LESSER
